README.md
setup.py
django_progressive.egg-info/PKG-INFO
django_progressive.egg-info/SOURCES.txt
django_progressive.egg-info/dependency_links.txt
django_progressive.egg-info/top_level.txt
django_pwa/__init__.py
django_pwa/settings.py
django_pwa/urls.py
django_pwa/utils.py
django_pwa/views.py
django_pwa/static/django_pwa/app.js
django_pwa/static/django_pwa/service-worker.js
django_pwa/static/django_pwa/worker-app.js
django_pwa/templates/load-manifest.html
django_pwa/templates/load-worker.html