Metadata-Version: 2.1
Name: django-progressive
Version: 1.0.3
Summary: Library for adding progressive web app functionality in your django project.
Home-page: https://github.com/m19t12/django-pwa
Author: Manolis Tsoukalas
Author-email: emmtsoukalas@gmail.com
License: GPL License
Platform: UNKNOWN
Classifier: Environment :: Web Environment
Classifier: Framework :: Django
Classifier: Framework :: Django :: 2.0
Classifier: Framework :: Django :: 3.0
Classifier: Intended Audience :: Developers
Classifier: License :: OSI Approved :: GNU General Public License v3 (GPLv3)
Classifier: Operating System :: OS Independent
Classifier: Programming Language :: Python
Classifier: Programming Language :: Python :: 3.6
Classifier: Programming Language :: Python :: 3.7
Classifier: Topic :: Internet :: WWW/HTTP
Classifier: Topic :: Internet :: WWW/HTTP :: Dynamic Content
